loren_frank_data_processing/DIO.py
loren_frank_data_processing/__init__.py
loren_frank_data_processing/core.py
loren_frank_data_processing/multiunit.py
loren_frank_data_processing/neurons.py
loren_frank_data_processing/position.py
loren_frank_data_processing/ripples.py
loren_frank_data_processing/saving.py
loren_frank_data_processing/task.py
loren_frank_data_processing/tetrodes.py
loren_frank_data_processing/track_segment_classification.py
loren_frank_data_processing/utilities.py
loren_frank_data_processing/visualization.py
loren_frank_data_processing/well_traversal_classification.py
loren_frank_data_processing-1.0.4.dist-info/LICENSE
loren_frank_data_processing-1.0.4.dist-info/METADATA
loren_frank_data_processing-1.0.4.dist-info/WHEEL
loren_frank_data_processing-1.0.4.dist-info/top_level.txt
loren_frank_data_processing-1.0.4.dist-info/RECORD
