Metadata-Version: 2.1
Name: loren-frank-data-processing
Version: 1.0.4
Summary: Import data from Loren Frank lab
Home-page: https://github.com/Eden-Kramer-Lab/loren_frank_data_processing
Author: Eric Denovellis
Author-email: edeno@bu.edu
License: GPL-3.0
License-File: LICENSE
Requires-Dist: numpy >=1.11
Requires-Dist: pandas >=0.18.0
Requires-Dist: scipy
Requires-Dist: xarray
Requires-Dist: netCDF4
Requires-Dist: dask
Requires-Dist: networkx >=2.0.0
Requires-Dist: matplotlib
